{
  "diarization": {
    "SPEAKER_00": 76
  },
  "asr": {
    " We are going to talk today about the sequel of Inconvenient Truth.": 1,
    "It's time again to talk about inconvenience.": 1,
    " Truth, a truth that everyone is concerned about, but nobody is willing to talk about.": 1,
    "Somebody has to take the lead, and I decided to do it.": 1,
    " If you are scared by global warming, wait until you will learn about local warming.": 1,
    "We will talk today about local warming.": 1,
    " Important health message.": 1,
    "Blogging may be hazardous to your health, especially if you are a male.": 1,
    " This message is given as a public service.": 1,
    " Blogging affect your posture.": 1,
    "We start with the posture.": 1,
    "This is the posture of ladies who are not blogging.": 1,
    "This is the posture of ladies who are blogging.": 1,
    " This is the natural poster of a man sitting squatting for ventilation purposes.": 1,
    " And this is a natural posture of a standing man.": 1,
    "And I think this picture inspired Chris to insert me into the lateral thinking session.": 1,
    "This is my blogging posture sitting.": 1,
    " And the result is, for greater comfort, men actually sit with their legs farther apart than women when walking on laptop.": 1,
    "However, they will adopt a less natural.": 1,
    " posture in order to balance it on their laps, which result in a significant rise of body heat between their thighs.": 1,
    "This is the issue of local warming.": 1,
    " This is a very This is a very serious newspaper.": 1,
    "It's Times of England very serious This is a very": 1,
    " Gentlemen and ladies, be serious.": 1,
    "This is a very serious research that you should read the underlined": 1,
    " And be careful, your jeans are in...": 1,
    " Will geeks become endangered species?": 1,
    " The fact population growth in countries with high laptop.": 1,
    "I need Hans Rosling to give me a grab.": 1,
    " Global warming.": 1,
    " But let's keep things in proportion.": 1,
    " How to take care in five easy steps.": 1,
    "First of all, you can use natural ventilation.": 1,
    "You can use body breath.": 1,
    " You should stay cool with the appropriate clothing.": 1,
    "You should care about your posture.": 1,
    "This is not right.": 1,
    "Can you extract from Chris another minute and a half for me?": 1,
    "Because I have a video I have to show you.": 1,
    " You are great!": 1,
    " This is the correct posture.": 1,
    "Another benefit of Wi-Fi.": 1,
    "We learned yesterday about the benefits of Wi-Fi.": 1,
    "Wi-Fi enable you to avoid the processor.": 1,
    " And there are some enhanced protection measures, which I would like to share with you.": 1,
    "And I would like in a minute to thank Phillips for helping.": 1,
    "This is a research which was done in 1986, but it's still valid.": 1,
    " Scrotum, I guess in plural, it's scrotum, like medium and media.": 1,
    " Digital Scrotum Digital Media.": 1,
    "And only last year I recognized that I'm a proud Scrotum owner.": 1,
    " And this research is being dissipated by the US government, so you can see that your tax money is working for good causes.": 1,
    " The Philips bodygroom has a sleek, ergonomic design for a safe and easy way to trim those scruffy underarm hairs.": 1,
    "The untidy curls on and around your b****, as well as the hard to reach locks on the underside of your b****.": 1,
    " Once you use the body groom, the world looks different.": 1,
    " And so does your... These days, with a hair free back, well groomed shoulders, and an extra optical inch on my...": 1,
    " Let's just say life has gotten pretty darn cozy.": 1,
    " This is one of the most popular viral advertisement of last year, known as the Optical Inch by Philips.": 1,
    "Let's applaud Philips.": 1,
    " For this gesture for humanity.": 1,
    " And this is how they are promoting the product.": 1,
    "I didn't touch it.": 1,
    "This is original.": 1,
    " Laptop used to solve overpopulation.": 1,
    " And if everything fails, there are some secondary uses for it.": 1,
    " And then our next talk, the next, Ted, if he invites me, will be why you should not carry a cell phone in your pocket.": 1,
    " And this is what the young generation says.": 1,
    " And I just want to show you that I'm not just preaching, but I also practice.": 1,
    " 4 am in the morning.": 1,
    " You cannot use this picture.": 1,
    " Now, I have some mini-themed prizes.": 1,
    "This is the Philips BodyGroom, one for our leader.": 1,
    " Anybody feel threatened?": 1,
    "Anybody really need it?": 1,
    " Any lady?": 1,
    "Any lady?": 1,
    " Thank you very much.": 1
  },
  "gender": {
    "male": 47
  },
  "age": {
    "31 - 45": 29,
    "46 - 65": 16,
    "23 - 30": 1,
    "18 - 22": 1
  },
  "emotion": {
    "happy": 43,
    "neutral": 3,
    "sad": 1
  },
  "positivity": {
    "positive": 38,
    "neutral": 8,
    "negative": 1
  },
  "strength": {
    "strong": 42,
    "neutral": 4,
    "weak": 1
  },
  "speaking_rate": {
    "normal": 37,
    "fast": 9,
    "slow": 1
  },
  "hesitation": {
    "no": 47
  },
  "engagement": {
    "engaged": 41,
    "neutral": 6
  },
  "politeness": {
    "polite": 41,
    "neutral": 6
  }
}